setup.cfg
setup.py
rtapi/__init__.py
rtapi/rt.py
rtapi.egg-info/PKG-INFO
rtapi.egg-info/SOURCES.txt
rtapi.egg-info/dependency_links.txt
rtapi.egg-info/requires.txt
rtapi.egg-info/top_level.txt