Metadata-Version: 1.1
Name: rtapi
Version: 0.2
Summary: Wrapper for RT API
Home-page: https://github.com/Rickerd0613/rtapi
Author: Jacob Rickerd
Author-email: jacobrickerd@gmail.com
License: MIT
Download-URL: https://github.com/peterldowns/rtapi/archive/0.2.tar.gz
Keywords: request,tracker,rt,api
Platform: UNKNOWN
